Metadata-Version: 1.0
Name: zdpytpol8projekt
Version: 0.0.2
Summary: super useful library
Home-page: UNKNOWN
Author: Krzysztof Lopatynski
Author-email: krzysztof.lopatynski@gmail.com
License: UNKNOWN
Platform: UNKNOWN
